MANIFEST.in
setup.cfg
setup.py
docs/HISTORY.txt
docs/LICENSE.txt
src/collective/__init__.py
src/collective.fb.egg-info/PKG-INFO
src/collective.fb.egg-info/SOURCES.txt
src/collective.fb.egg-info/dependency_links.txt
src/collective.fb.egg-info/entry_points.txt
src/collective.fb.egg-info/namespace_packages.txt
src/collective.fb.egg-info/not-zip-safe
src/collective.fb.egg-info/requires.txt
src/collective.fb.egg-info/top_level.txt
src/collective/fb/__init__.py
src/collective/fb/interfaces.py