Metadata-Version: 1.0
Name: collective.fb
Version: 1.0
Summary: Plone Facebook integration bundle
Home-page: http://plone.org/products/collective.fb
Author: Massimo Azzolini, Mauro Amico, Andrzej Mleczko
Author-email: sviluppoplone@redturtle.it
License: GPL
Platform: UNKNOWN
Classifier: Programming Language :: Python
Classifier: Topic :: Software Development :: Libraries :: Python Modules
